crllm/__init__.py
crllm/app.py
crllm/cli.py
crllm/code/code_loader.py
crllm/code/loaders/__init__.py
crllm/code/loaders/exceptions/__init__.py
crllm/code/loaders/exceptions/no_code_found.py
crllm/code/loaders/file.py
crllm/code/loaders/git.py
crllm/code/loaders/git_compare.py
crllm/code/loaders/ignore_utils.py
crllm/config/__init__.py
crllm/config/config.toml
crllm/config/config_service.py
crllm/init_project.py
crllm/model/__init__.py
crllm/model/model.py
crllm/model/model_factory.py
crllm/model/provider/__init__.py
crllm/model/provider/azure.py
crllm/model/provider/dryrun.py
crllm/model/provider/huggingface.py
crllm/model/provider/ollama.py
crllm/model/provider/openai.py
crllm/prompt_builder.py
crllm/test/functional/code/loaders/file/file_test.py
crllm/test/functional/code/loaders/file/foo.txt
crllm/test/functional/config.toml
crllm/test/functional/init_project_test.py
crllm/test/functional/smoke_test.py
crllm/test/unit/code/loaders/ignore_utils_test.py
crllm/test/unit/config/config_service_test.py
crllm-0.5.0.dist-info/LICENSE
crllm-0.5.0.dist-info/METADATA
crllm-0.5.0.dist-info/WHEEL
crllm-0.5.0.dist-info/entry_points.txt
crllm-0.5.0.dist-info/RECORD
