Metadata-Version: 2.1
Name: crllm
Version: 0.5.0
Summary: Provides AI-powered code reviews using local or cloud-based Large Language Models (LLMs) to help developers improve code quality and catch bugs efficiently.
Home-page: https://lukasrump.github.io/crllm/
License: MIT
Keywords: code review,AI,LLM,static analysis,cli
Author: Lukas Rump
Requires-Python: >=3.10,<4.0
Classifier: License :: OSI Approved :: MIT License
Classifier: Programming Language :: Python :: 3
Classifier: Programming Language :: Python :: 3.10
Classifier: Programming Language :: Python :: 3.11
Classifier: Programming Language :: Python :: 3.12
Classifier: Programming Language :: Python :: 3.13
Requires-Dist: argparse (>=1.4.0,<2.0.0)
Requires-Dist: coverage (>=7.6.1,<8.0.0)
Requires-Dist: deepmerge (>=2.0,<3.0)
Requires-Dist: faiss-cpu (>=1.9.0,<2.0.0)
Requires-Dist: gitpython (>=3.1.43,<4.0.0)
Requires-Dist: inquirer (>=3.4.0,<4.0.0)
Requires-Dist: langchain (>=0.3.1,<0.4.0)
Requires-Dist: langchain-community (>=0.3.3,<0.4.0)
Requires-Dist: langchain-huggingface (>=0.1.0,<0.2.0)
Requires-Dist: langchain-ollama (>=0.2.0,<0.3.0)
Requires-Dist: langchain-openai (>=0.2.1,<0.3.0)
Requires-Dist: rich (>=13.8.1,<14.0.0)
Requires-Dist: toml (>=0.10.2,<0.11.0)
Requires-Dist: tree-sitter (>=0.21.3,<0.22.0)
Requires-Dist: tree-sitter-languages (>=1.10.2,<2.0.0)
Project-URL: Repository, https://github.com/lukasrump/crllm
